topsis_python/topsis.py
Topsis_Anureet_Kaur_102003146-0.0.2.dist-info/LICENSE
Topsis_Anureet_Kaur_102003146-0.0.2.dist-info/METADATA
Topsis_Anureet_Kaur_102003146-0.0.2.dist-info/WHEEL
Topsis_Anureet_Kaur_102003146-0.0.2.dist-info/entry_points.txt
Topsis_Anureet_Kaur_102003146-0.0.2.dist-info/top_level.txt
Topsis_Anureet_Kaur_102003146-0.0.2.dist-info/RECORD
